matplot2tikz/__about__.py
matplot2tikz/__init__.py
matplot2tikz/_axes.py
matplot2tikz/_cleanfigure.py
matplot2tikz/_color.py
matplot2tikz/_files.py
matplot2tikz/_hatches.py
matplot2tikz/_image.py
matplot2tikz/_legend.py
matplot2tikz/_line2d.py
matplot2tikz/_markers.py
matplot2tikz/_patch.py
matplot2tikz/_path.py
matplot2tikz/_quadmesh.py
matplot2tikz/_save.py
matplot2tikz/_text.py
matplot2tikz/_tikzdata.py
matplot2tikz/_util.py
matplot2tikz-0.5.1.dist-info/licenses/LICENSE
matplot2tikz-0.5.1.dist-info/METADATA
matplot2tikz-0.5.1.dist-info/WHEEL
matplot2tikz-0.5.1.dist-info/top_level.txt
matplot2tikz-0.5.1.dist-info/RECORD
