Metadata-Version: 2.4
Name: matplot2tikz
Version: 0.5.1
Summary: Convert matplotlib figures into TikZ/PGFPlots
Author-email: Erwin de Gelder <erwindegelder@gmail.com>, Nico Schlömer <nico.schloemer@gmail.com>
License-Expression: MIT
Keywords: latex,tikz,matplotlib,graphics
Classifier: Programming Language :: Python :: 3
Classifier: Programming Language :: Python :: 3.10
Classifier: Programming Language :: Python :: 3.11
Classifier: Programming Language :: Python :: 3.12
Classifier: Programming Language :: Python :: 3.13
Classifier: Programming Language :: Python :: 3.14
Requires-Python: >=3.10
License-File: LICENSE
Requires-Dist: matplotlib>=1.4.0
Requires-Dist: numpy
Requires-Dist: Pillow
Requires-Dist: webcolors
Requires-Dist: typing_extensions>=4.5
Provides-Extra: lint
Requires-Dist: mypy; extra == "lint"
Requires-Dist: ruff; extra == "lint"
Provides-Extra: test
Requires-Dist: pytest>=7.4.1; extra == "test"
Requires-Dist: pytest-cov>=6.0.0; extra == "test"
Requires-Dist: coverage[toml]>=7.0.0; extra == "test"
Requires-Dist: typeguard>=4.4.0; extra == "test"
Requires-Dist: pandas; extra == "test"
Provides-Extra: dev
Requires-Dist: tox; extra == "dev"
Requires-Dist: tox-pyenv-redux; extra == "dev"
Requires-Dist: mypy; extra == "dev"
Requires-Dist: ruff; extra == "dev"
Requires-Dist: pytest>=7.4.1; extra == "dev"
Requires-Dist: pytest-cov>=6.0.0; extra == "dev"
Requires-Dist: coverage[toml]>=7.0.0; extra == "dev"
Requires-Dist: typeguard>=4.4.0; extra == "dev"
Dynamic: license-file
